typetidy/__init__.py
typetidy-0.1.0.dist-info/METADATA
typetidy-0.1.0.dist-info/WHEEL
typetidy-0.1.0.dist-info/RECORD
