Metadata-Version: 2.1
Name: typetidy
Version: 0.1.0
Summary: A linting tool to move typing imports into an optional block
License: MIT
Author: Weevils.io
Author-email: code@weevils.io
Requires-Python: >=3.8,<4.0
Classifier: License :: OSI Approved :: MIT License
Classifier: Programming Language :: Python :: 3
Classifier: Programming Language :: Python :: 3.8
Classifier: Programming Language :: Python :: 3.9
Classifier: Programming Language :: Python :: 3.10
Classifier: Programming Language :: Python :: 3.11
